range_inf/__init__.py
range_inf/test.py
range_inf-0.0.0.dist-info/METADATA
range_inf-0.0.0.dist-info/WHEEL
range_inf-0.0.0.dist-info/top_level.txt
range_inf-0.0.0.dist-info/RECORD
